openhands/sdk/__init__.py
openhands/sdk/py.typed
openhands/sdk/agent/__init__.py
openhands/sdk/agent/agent.py
openhands/sdk/agent/base.py
openhands/sdk/agent/utils.py
openhands/sdk/agent/prompts/in_context_learning_example.j2
openhands/sdk/agent/prompts/in_context_learning_example_suffix.j2
openhands/sdk/agent/prompts/security_policy.j2
openhands/sdk/agent/prompts/security_risk_assessment.j2
openhands/sdk/agent/prompts/self_documentation.j2
openhands/sdk/agent/prompts/system_prompt.j2
openhands/sdk/agent/prompts/system_prompt_interactive.j2
openhands/sdk/agent/prompts/system_prompt_long_horizon.j2
openhands/sdk/agent/prompts/system_prompt_planning.j2
openhands/sdk/agent/prompts/system_prompt_tech_philosophy.j2
openhands/sdk/agent/prompts/model_specific/anthropic_claude.j2
openhands/sdk/agent/prompts/model_specific/google_gemini.j2
openhands/sdk/agent/prompts/model_specific/openai_gpt/gpt-5-codex.j2
openhands/sdk/agent/prompts/model_specific/openai_gpt/gpt-5.j2
openhands/sdk/context/__init__.py
openhands/sdk/context/agent_context.py
openhands/sdk/context/view.py
openhands/sdk/context/condenser/__init__.py
openhands/sdk/context/condenser/base.py
openhands/sdk/context/condenser/llm_summarizing_condenser.py
openhands/sdk/context/condenser/no_op_condenser.py
openhands/sdk/context/condenser/pipeline_condenser.py
openhands/sdk/context/condenser/utils.py
openhands/sdk/context/condenser/prompts/summarizing_prompt.j2
openhands/sdk/context/prompts/__init__.py
openhands/sdk/context/prompts/prompt.py
openhands/sdk/context/prompts/templates/ask_agent_template.j2
openhands/sdk/context/prompts/templates/skill_knowledge_info.j2
openhands/sdk/context/prompts/templates/system_message_suffix.j2
openhands/sdk/context/skills/__init__.py
openhands/sdk/context/skills/exceptions.py
openhands/sdk/context/skills/skill.py
openhands/sdk/context/skills/trigger.py
openhands/sdk/context/skills/types.py
openhands/sdk/context/skills/utils.py
openhands/sdk/conversation/__init__.py
openhands_sdk-1.10.0.dist-info/METADATA
openhands_sdk-1.10.0.dist-info/WHEEL
openhands_sdk-1.10.0.dist-info/top_level.txt
openhands_sdk-1.10.0.dist-info/RECORD
