Metadata-Version: 2.4
Name: openhands-sdk
Version: 1.10.0
Summary: OpenHands SDK - Core functionality for building AI agents
Project-URL: Source, https://github.com/OpenHands/software-agent-sdk
Project-URL: Homepage, https://github.com/OpenHands/software-agent-sdk
Project-URL: Documentation, https://docs.openhands.dev/sdk
Project-URL: Bug Tracker, https://github.com/OpenHands/software-agent-sdk/issues
Requires-Python: >=3.12
Requires-Dist: deprecation>=2.1.0
Requires-Dist: fastmcp>=2.11.3
Requires-Dist: filelock>=3.20.1
Requires-Dist: httpx>=0.27.0
Requires-Dist: litellm>=1.80.10
Requires-Dist: pydantic>=2.12.5
Requires-Dist: python-frontmatter>=1.1.0
Requires-Dist: python-json-logger>=3.3.0
Requires-Dist: tenacity>=9.1.2
Requires-Dist: websockets>=12
Requires-Dist: lmnr>=0.7.24
Provides-Extra: boto3
Requires-Dist: boto3>=1.35.0; extra == "boto3"
